bpy_helper/__init__.py
bpy_helper/camera.py
bpy_helper/geometry.py
bpy_helper/io.py
bpy_helper/light.py
bpy_helper/material.py
bpy_helper/mesh.py
bpy_helper/random.py
bpy_helper/scene.py
bpy_helper/utils.py
bpy_helper-0.0.13.dist-info/licenses/LICENSE
bpy_helper-0.0.13.dist-info/METADATA
bpy_helper-0.0.13.dist-info/WHEEL
bpy_helper-0.0.13.dist-info/top_level.txt
bpy_helper-0.0.13.dist-info/RECORD
