Metadata-Version: 2.4
Name: bpy_helper
Version: 0.0.13
Summary: A lightweight alternative to BlenderProc
Author-email: NCJ <me@ncj.wiki>
License-Expression: MIT
Project-URL: homepage, https://github.com/iamNCJ/bpy-helper
Classifier: Programming Language :: Python :: 3
Classifier: Operating System :: POSIX :: Linux
Classifier: Operating System :: MacOS
Classifier: Topic :: Multimedia :: Graphics :: 3D Rendering
Requires-Python: >=3.10
License-File: LICENSE
Requires-Dist: bpy>=3.4.0
Requires-Dist: numpy
Dynamic: license-file
